metaflow_extensions/netflix_ext/generate_vendor.py
metaflow_extensions/netflix_ext/cmd/mfextinit_netflixext.py
metaflow_extensions/netflix_ext/cmd/debug/__init__.py
metaflow_extensions/netflix_ext/cmd/debug/constants.py
metaflow_extensions/netflix_ext/cmd/debug/current_stub_generator.py
metaflow_extensions/netflix_ext/cmd/debug/debug_cmd.py
metaflow_extensions/netflix_ext/cmd/debug/debug_script_generator.py
metaflow_extensions/netflix_ext/cmd/debug/debug_stub_generator.py
metaflow_extensions/netflix_ext/cmd/debug/debug_utils.py
metaflow_extensions/netflix_ext/cmd/debug/jupyter_instructions_markdown.py
metaflow_extensions/netflix_ext/cmd/debug/jupyter_title_markdown.py
metaflow_extensions/netflix_ext/cmd/environment/__init__.py
metaflow_extensions/netflix_ext/cmd/environment/environment_cmd.py
metaflow_extensions/netflix_ext/cmd/environment/utils.py
metaflow_extensions/netflix_ext/config/mfextinit_netflixext.py
metaflow_extensions/netflix_ext/plugins/environment_cli.py
metaflow_extensions/netflix_ext/plugins/mfextinit_netflixext.py
metaflow_extensions/netflix_ext/plugins/conda/__init__.py
metaflow_extensions/netflix_ext/plugins/conda/conda.py
metaflow_extensions/netflix_ext/plugins/conda/conda_common_decorator.py
metaflow_extensions/netflix_ext/plugins/conda/conda_environment.py
metaflow_extensions/netflix_ext/plugins/conda/conda_flow_decorator.py
metaflow_extensions/netflix_ext/plugins/conda/conda_lock_micromamba_server.py
metaflow_extensions/netflix_ext/plugins/conda/conda_step_decorator.py
metaflow_extensions/netflix_ext/plugins/conda/env_descr.py
metaflow_extensions/netflix_ext/plugins/conda/envsresolver.py
metaflow_extensions/netflix_ext/plugins/conda/parsers.py
metaflow_extensions/netflix_ext/plugins/conda/pypi_package_builder.py
metaflow_extensions/netflix_ext/plugins/conda/remote_bootstrap.py
metaflow_extensions/netflix_ext/plugins/conda/terminal_menu.py
metaflow_extensions/netflix_ext/plugins/conda/utils.py
metaflow_netflixext-1.3.1.dist-info/licenses/LICENSE
metaflow_netflixext-1.3.1.dist-info/METADATA
metaflow_netflixext-1.3.1.dist-info/WHEEL
metaflow_netflixext-1.3.1.dist-info/top_level.txt
metaflow_netflixext-1.3.1.dist-info/RECORD
