Metadata-Version: 2.4
Name: metaflow-netflixext
Version: 1.3.1
Summary: Metaflow extensions from Netflix
Author: Netflix Metaflow Developers
Author-email: metaflow-dev@netflix.com
License: Apache Software License
Project-URL: Source, https://github.com/Netflix/metaflow-nflx-extensions
Project-URL: Tracker, https://github.com/Netflix/metaflow-nflx-extensions/issues
Classifier: Development Status :: 5 - Production/Stable
Classifier: License :: OSI Approved :: Apache Software License
Classifier: Operating System :: MacOS :: MacOS X
Classifier: Operating System :: POSIX :: Linux
Classifier: Programming Language :: Python :: 3
Classifier: Programming Language :: Python :: 3.7
Classifier: Programming Language :: Python :: 3.8
Classifier: Programming Language :: Python :: 3.9
Classifier: Programming Language :: Python :: 3.10
Classifier: Programming Language :: Python :: 3.11
Classifier: Programming Language :: Python :: 3.12
Classifier: Programming Language :: Python :: 3.13
Requires-Python: >=3.7.2
License-File: LICENSE
Requires-Dist: metaflow>=2.16.0
Dynamic: author
Dynamic: author-email
Dynamic: classifier
Dynamic: description
Dynamic: description-content-type
Dynamic: license
Dynamic: license-file
Dynamic: project-url
Dynamic: requires-dist
Dynamic: requires-python
Dynamic: summary
